python_simhash-0.1.0.dist-info/METADATA
python_simhash-0.1.0.dist-info/WHEEL
simhash/__init__.py
simhash/_simhash.pyi
simhash/py.typed
simhash/_simhash.abi3.so
python_simhash-0.1.0.dist-info/RECORD
