Metadata-Version: 2.4
Name: python-simhash
Version: 0.1.0
Classifier: Programming Language :: Rust
Classifier: Programming Language :: Python :: Implementation :: CPython
Classifier: Programming Language :: Python :: Implementation :: PyPy
Summary: SimHash algorithm implementation in Rust for Python
Author-email: Tim Pogue <tim@emergentmethods.ai>
License: MIT
Requires-Python: >=3.10, <4.0
Project-URL: repository, https://gitlab.com/emergentmethods/simhash
